rcx_tk/__init__.py
rcx_tk/__main__.py
rcx_tk/process_metadata_file.py
rcx_tk/py.typed
rcx_tk-0.1.0.dist-info/LICENSE
rcx_tk-0.1.0.dist-info/METADATA
rcx_tk-0.1.0.dist-info/WHEEL
rcx_tk-0.1.0.dist-info/entry_points.txt
rcx_tk-0.1.0.dist-info/RECORD
