Metadata-Version: 2.1
Name: rcx-tk
Version: 0.1.0
Summary: This package adjusts and cleans the metadata file provided by a user.
License: MIT
Keywords: metadata,alkanes,metabolomics
Author: Zargham Ahmad
Author-email: zargham.ahmad@recetox.muni.cz
Requires-Python: >=3.11,<4.0
Classifier: License :: OSI Approved :: MIT License
Classifier: Programming Language :: Python :: 3
Classifier: Programming Language :: Python :: 3.11
Classifier: Programming Language :: Python :: 3.12
Requires-Dist: click (>=8.1.7,<9.0.0)
Requires-Dist: mypy (>=1.10.1,<2.0.0)
Requires-Dist: pandas (>=2.2.2,<3.0.0)
Requires-Dist: pandas-stubs (>=2.2.2.240603,<3.0.0.0)
Requires-Dist: pyxlsx (>=1.1.3,<2.0.0)
